odoo/addons/base_user_role_company/README.rst
odoo/addons/base_user_role_company/__init__.py
odoo/addons/base_user_role_company/__manifest__.py
odoo/addons/base_user_role_company/i18n/base_user_role_company.pot
odoo/addons/base_user_role_company/i18n/de.po
odoo/addons/base_user_role_company/models/__init__.py
odoo/addons/base_user_role_company/models/ir_http.py
odoo/addons/base_user_role_company/models/role.py
odoo/addons/base_user_role_company/readme/CONFIGURE.rst
odoo/addons/base_user_role_company/readme/CONTRIBUTORS.rst
odoo/addons/base_user_role_company/readme/DESCRIPTION.rst
odoo/addons/base_user_role_company/readme/USAGE.rst
odoo/addons/base_user_role_company/static/description/icon.png
odoo/addons/base_user_role_company/static/description/index.html
odoo/addons/base_user_role_company/tests/__init__.py
odoo/addons/base_user_role_company/tests/test_role_per_company.py
odoo/addons/base_user_role_company/views/role.xml
odoo12_addon_base_user_role_company-12.0.1.0.0.99.dev7.dist-info/METADATA
odoo12_addon_base_user_role_company-12.0.1.0.0.99.dev7.dist-info/WHEEL
odoo12_addon_base_user_role_company-12.0.1.0.0.99.dev7.dist-info/top_level.txt
odoo12_addon_base_user_role_company-12.0.1.0.0.99.dev7.dist-info/RECORD
